{
  "subreddit": "Bitcoin",
  "timeframe": "day",
  "posts": [
    {
      "title": "At least \ud83e\udd37\u200d\u2642\ufe0f",
      "author": "MrMBTC",
      "url": "https://www.reddit.com/r/Bitcoin/comments/1p36td6/at_least/",
      "published": 1763750842.0,
      "thumbnail": "https://preview.redd.it/n7vlc48son2g1.jpeg?width=640&crop=smart&auto=webp&s=88b924e6bf61485a0ef64da9b6b762f491a661f0",
      "external_url": null,
      "site_name": null,
      "favicon": null,
      "description": null
    },
    {
      "title": "My crystal ball just told me BTC will be back at 100k in mid-December.",
      "author": "xSpAcEX7",
      "url": "https://www.reddit.com/r/Bitcoin/comments/1p3b3c8/my_crystal_ball_just_told_me_btc_will_be_back_at/",
      "published": 1763760921.0,
      "thumbnail": "https://preview.redd.it/yfi8irdrio2g1.gif?width=216&crop=smart&s=13b456b21214251a33ebb635a36bdf815ada221d",
      "external_url": null,
      "site_name": null,
      "favicon": null,
      "description": "Idk why you guys are panic selling\u2026 The orb has spoken. The prophecy is set. The candles will rise again."
    },
    {
      "title": "How was the moon ser?",
      "author": "bitcoin-machinegun",
      "url": "https://www.reddit.com/r/Bitcoin/comments/1p3n0qo/how_was_the_moon_ser/",
      "published": 1763795719.0,
      "thumbnail": "https://preview.redd.it/b3reota8er2g1.jpeg?width=640&crop=smart&auto=webp&s=dcff32d2986a52347af9ed7b0a705e19205f62c9",
      "external_url": null,
      "site_name": null,
      "favicon": null,
      "description": "xD"
    },
    {
      "title": "Thanks for the extra ketchup packets Diamond Hands",
      "author": "yoobermcruber",
      "url": "https://www.reddit.com/r/Bitcoin/comments/1p3gqkf/thanks_for_the_extra_ketchup_packets_diamond_hands/",
      "published": 1763775559.0,
      "thumbnail": "https://preview.redd.it/qtsoti7aqp2g1.jpeg?width=640&crop=smart&auto=webp&s=affee76cc75da6d9fa8b9c942bb1a62718935a37",
      "external_url": null,
      "site_name": null,
      "favicon": null,
      "description": null
    },
    {
      "title": "When BTC dips and suddenly the wedding becomes Q4 2032",
      "author": "qbanboy14",
      "url": "https://www.reddit.com/r/Bitcoin/comments/1p3d1q4/when_btc_dips_and_suddenly_the_wedding_becomes_q4/",
      "published": 1763765689.0,
      "thumbnail": "https://external-preview.redd.it/Y2V2eDRmcXh3bzJnMafYyXFohqV-xOGa-PyH0LRAwHHxQh2UDxkKtLlalC0A.png?width=640&crop=smart&auto=webp&s=80f55078fbdca09b124efe0ea3dcc47b45551c8a",
      "external_url": null,
      "site_name": null,
      "favicon": null,
      "description": null
    },
    {
      "title": "Every bitcoiner reaction right now:",
      "author": "unthocks",
      "url": "https://www.reddit.com/r/Bitcoin/comments/1p3p1yw/every_bitcoiner_reaction_right_now/",
      "published": 1763803646.0,
      "thumbnail": "https://preview.redd.it/yoocf2hr1s2g1.jpeg?width=640&crop=smart&auto=webp&s=da6508ea0fc6e669ae46c61cbc8416d434c89cfc",
      "external_url": null,
      "site_name": null,
      "favicon": null,
      "description": null
    },
    {
      "title": "People who are selling right now, really do not understand bitcoin",
      "author": "New-Ad-9629",
      "url": "https://www.reddit.com/r/Bitcoin/comments/1p3axvs/people_who_are_selling_right_now_really_do_not/",
      "published": 1763760558.0,
      "thumbnail": null,
      "external_url": null,
      "site_name": null,
      "favicon": null,
      "description": "We are living in uncertain times: Geopolitical tensions, domestic political uncertainty, AI bubble, Sovereign debt crisis (in several countries), falling employment, and a climate crisis due to global warming. Bitcoin has never been so relevant until now. To beat the uncertainty, you need something that is certain -- and that's 21 million. Whatever happens to the world, this number will never change. The worse the economy and markets get, the better the case for bitcoin. That is why it is called 'digital gold', and hope people realize this sooner rather than later. Smart money is already buying the bitcoin that retail is selling. The best time to buy bitcoin was in the first few yrs after it was invented. The second best time is now. Please study bitcoin, and try to understand it. Do not sell. Buy."
    },
    {
      "title": "Well well well, looks like the pump is on next week \ud83d\ude80\ud83d\ude80\ud83d\ude80",
      "author": "TheUnholyMoly",
      "url": "https://www.reddit.com/r/Bitcoin/comments/1p3av2c/well_well_well_looks_like_the_pump_is_on_next_week/",
      "published": 1763760369.0,
      "thumbnail": "https://preview.redd.it/n84vj5a4ho2g1.jpeg?width=640&crop=smart&auto=webp&s=e28bf87f1c15b4866382b0d40b88cc7527bcb232",
      "external_url": null,
      "site_name": null,
      "favicon": null,
      "description": null
    },
    {
      "title": "Why is everyone selling? Isn\u2019t this the best time to buy more?",
      "author": "Known_Code6832",
      "url": "https://www.reddit.com/r/Bitcoin/comments/1p39u9c/why_is_everyone_selling_isnt_this_the_best_time/",
      "published": 1763757944.0,
      "thumbnail": null,
      "external_url": null,
      "site_name": null,
      "favicon": null,
      "description": "I don\u2019t completely understand bitcoin but I know enough that historically the crazy dips are right before the market skyrockets. Why do people not think it will happen again?"
    },
    {
      "title": "Robert Kiyosaki is scam",
      "author": "LittlePrince6987",
      "url": "https://www.reddit.com/r/Bitcoin/comments/1p3o9r2/robert_kiyosaki_is_scam/",
      "published": 1763800536.0,
      "thumbnail": "https://preview.redd.it/gm9t750ksr2g1.jpeg?width=640&crop=smart&auto=webp&s=d8c2074ffd3e3c8b4e5e6a2dd7e297bc26f4ca8c",
      "external_url": null,
      "site_name": null,
      "favicon": null,
      "description": "And in debt \ud83d\ude43"
    }
  ],
  "fetched_at": "2025-11-22T16:34:06.375443+00:00"
}