{
  "subreddit": "Bitcoin",
  "posts": [
    {
      "title": "Yes! Shush \ud83e\udd2b",
      "author": "ScrewTheBanker",
      "url": "https://www.reddit.com/r/Bitcoin/comments/1p6lvka/yes_shush/",
      "published": 1764098856.0,
      "thumbnail": "https://preview.redd.it/jbg9772mfg3g1.jpeg?width=640&crop=smart&auto=webp&s=ed481aeb922740ade24779403f207a3936d09c18",
      "external_url": null,
      "site_name": null,
      "favicon": null,
      "description": null
    },
    {
      "title": "I hit a milestone \ud83d\udc4f\ud83e\ude99",
      "author": "MoistGameplays",
      "url": "https://www.reddit.com/r/Bitcoin/comments/1p6nlzj/i_hit_a_milestone/",
      "published": 1764102744.0,
      "thumbnail": "https://preview.redd.it/p0gftsa6rg3g1.png?width=640&crop=smart&auto=webp&s=2117fef400d4306866c0bc92ba2167598ddc936c",
      "external_url": null,
      "site_name": null,
      "favicon": null,
      "description": "I love the discount lately \ud83d\udc4f\ud83e\ude99 hope it drops more"
    },
    {
      "title": "150k? Will be soon\u2026",
      "author": "DardMiner1982",
      "url": "https://www.reddit.com/r/Bitcoin/comments/1p6pb8k/150k_will_be_soon/",
      "published": 1764106628.0,
      "thumbnail": "https://preview.redd.it/8tpef41q2h3g1.jpeg?width=640&crop=smart&auto=webp&s=345a9fe30a8e7ba25791d23cf59e17b87f16e82c",
      "external_url": null,
      "site_name": null,
      "favicon": null,
      "description": null
    },
    {
      "title": "The Great State of Texas Acquires Bitcoin",
      "author": "TeaGroundbreaking306",
      "url": "https://www.reddit.com/r/Bitcoin/comments/1p6n7k7/the_great_state_of_texas_acquires_bitcoin/",
      "published": 1764101831.0,
      "thumbnail": "https://preview.redd.it/ni68clkgog3g1.jpeg?width=640&crop=smart&auto=webp&s=87879463023b530401985178bf1820b0bd7e8d66",
      "external_url": null,
      "site_name": null,
      "favicon": null,
      "description": "One domino at a time, Bitcoin will become self evident."
    },
    {
      "title": "Bitcoin is doing exactly what it needs to do.",
      "author": "Legal_Technician9455",
      "url": "https://www.reddit.com/r/Bitcoin/comments/1p6szjf/bitcoin_is_doing_exactly_what_it_needs_to_do/",
      "published": 1764115767.0,
      "thumbnail": null,
      "external_url": null,
      "site_name": null,
      "favicon": null,
      "description": "First, by eliminating traders and those who use leverage, the ones who always lose money in the markets. Second, by crushing altcoin holders\u2014you deserve it. And third, by targeting retail investors (those of you reading this), people with an average IQ of 90 who say, \"Bro, Bitcoin's going to crash, I'm going to sell and buy back later, that's what the 4-year cycle says, a 22-year-old YouTuber with a Lamborghini told me.\" And that's how they get the perfect setup for a good bull year in 2026. But who knows?"
    },
    {
      "title": "God-tier \ud83d\ude80",
      "author": "MrMBTC",
      "url": "https://www.reddit.com/r/Bitcoin/comments/1p6ize5/godtier/",
      "published": 1764092557.0,
      "thumbnail": "https://preview.redd.it/0xfpj3uvwf3g1.jpeg?width=640&crop=smart&auto=webp&s=1eaa9bff6e7d667c362eb924fb85cc3ba549a4ec",
      "external_url": null,
      "site_name": null,
      "favicon": null,
      "description": null
    },
    {
      "title": "90K TOMORROW! SOON AS WE\u2019RE IN BUSINESS!",
      "author": "sentientchimpman",
      "url": "https://www.reddit.com/r/Bitcoin/comments/1p6vg4p/90k_tomorrow_soon_as_were_in_business/",
      "published": 1764122565.0,
      "thumbnail": "https://preview.redd.it/s50rdb54ei3g1.gif?width=320&crop=smart&s=6f975c5f401802ff9db55de52bcc6ca6fe1a3ec2",
      "external_url": null,
      "site_name": null,
      "favicon": null,
      "description": null
    },
    {
      "title": "$89,000 Bitcoin Today vs Last Week",
      "author": "SolidityScan",
      "url": "https://www.reddit.com/r/Bitcoin/comments/1p6g00b/89000_bitcoin_today_vs_last_week/",
      "published": 1764085976.0,
      "thumbnail": "https://preview.redd.it/jmkxxv89df3g1.png?width=640&crop=smart&auto=webp&s=eca9f908bb2a5218bb648d7f2fb89127b988c821",
      "external_url": null,
      "site_name": null,
      "favicon": null,
      "description": null
    },
    {
      "title": "So which one is it?",
      "author": "Loud_Permission1903",
      "url": "https://www.reddit.com/r/Bitcoin/comments/1p6w1vd/so_which_one_is_it/",
      "published": 1764124293.0,
      "thumbnail": "https://preview.redd.it/kqc6sgm8ji3g1.jpeg?width=640&crop=smart&auto=webp&s=2f8cc6bf3f91578314ded85da76ecf79950a6816",
      "external_url": null,
      "site_name": null,
      "favicon": null,
      "description": null
    },
    {
      "title": "Bitcoin is interesting market",
      "author": "Nearing_retirement",
      "url": "https://www.reddit.com/r/Bitcoin/comments/1p6x4a2/bitcoin_is_interesting_market/",
      "published": 1764127394.0,
      "thumbnail": null,
      "external_url": null,
      "site_name": null,
      "favicon": null,
      "description": "I have worked for hedge fund for 25 years. Have made lots of money in bonuses. Just my take on Bitcoin is that it is interesting. The blockchain is different from a standard exchange. With a regular exchange you don\u2019t know who is buying or selling. The exchange hides that information. With Bitcoin blockchain there are public addresses. Likely some funds are making a fortune analyzing the blockchain buys and sells. My take is long term Bitcoin is a good bet."
    }
  ],
  "fetched_at": "2025-11-26T06:42:57.235900+00:00"
}