{
  "title": "YouTube Videos",
  "query": "ethereum",
  "order": "relevance",
  "videos": [
    {
      "video_id": "ufxKb5GmsSg",
      "title": "Tom Lee: &quot;The Ethereum Price Is About To Get Out Of Control&quot;",
      "description": "LIMITED TIME: 50% deposit bonus on first $10000 - (sign up on CoinW): ...",
      "channel_name": "Altcoin Daily",
      "channel_id": "UCbLhGKVY-bJPcawebgtNfbw",
      "thumbnail": "https://i.ytimg.com/vi/ufxKb5GmsSg/hqdefault.jpg",
      "published_at": 1764898534.0,
      "url": "https://www.youtube.com/watch?v=ufxKb5GmsSg",
      "duration": "11:16",
      "view_count": 29895,
      "view_count_display": "30K",
      "like_count": 2521,
      "like_count_display": "3K",
      "comment_count": 300,
      "comment_count_display": "300",
      "channel_avatar": "https://yt3.ggpht.com/ytc/AIdro_ndZORygyaaS9NAs9gaLWYqTdF3NSmsKoZoSzWtRRtslUI=s88-c-k-c0x00ffffff-no-rj"
    },
    {
      "video_id": "rYEgr3YN-qI",
      "title": "Ethereum Fusaka Upgrade Is HERE!! Is ETH About To EXPLODE!?",
      "description": "While everyone watched Bitcoin break resistance, Ethereum quietly shipped Fusaka \u2014 a live upgrade that radically improves ...",
      "channel_name": "Coin Bureau",
      "channel_id": "UCqK_GSMbpiV8spgD3ZGloSw",
      "thumbnail": "https://i.ytimg.com/vi/rYEgr3YN-qI/hqdefault.jpg",
      "published_at": 1764869264.0,
      "url": "https://www.youtube.com/watch?v=rYEgr3YN-qI",
      "duration": "17:37",
      "view_count": 23130,
      "view_count_display": "23K",
      "like_count": 1539,
      "like_count_display": "2K",
      "comment_count": 125,
      "comment_count_display": "125",
      "channel_avatar": "https://yt3.ggpht.com/ytc/AIdro_mir_9R_w9VCBNv2_PZnY3Q5fm5tkr8c0EXFTMaG9nPMA=s88-c-k-c0x00ffffff-no-rj"
    },
    {
      "video_id": "PtCcS9c-GP4",
      "title": "Tom Lee: The Crypto SUPERCYCLE Is Still Alive... &amp; Ethereum Is Going to LEAD!",
      "description": "Wall Street legend Tom Lee joins Binance Blockchain Week 2025 to break down why he believes the crypto supercycle is still ...",
      "channel_name": "Binance",
      "channel_id": "UCfYw6dhiwGBJQY_-Jcs8ozw",
      "thumbnail": "https://i.ytimg.com/vi/PtCcS9c-GP4/hqdefault.jpg",
      "published_at": 1764871229.0,
      "url": "https://www.youtube.com/watch?v=PtCcS9c-GP4",
      "duration": "27:33",
      "view_count": 47519,
      "view_count_display": "48K",
      "like_count": 1880,
      "like_count_display": "2K",
      "comment_count": 341,
      "comment_count_display": "341",
      "channel_avatar": "https://yt3.ggpht.com/KbadoYwdXl5QjjkAfY7cxwLRVd_Lvd62bE7VrHeHNJGqJr163D8XTUMWy231J0eS1lLWaS9GUro=s88-c-k-c0x00ffffff-no-rj"
    },
    {
      "video_id": "jJ_5Lv0dESU",
      "title": "\ud83d\udea8 ETH Is About To BREAK OUT \u2014 The Level Everyone Is Watching",
      "description": "Real-time crypto analysis \u2014 join my VIP Telegram.",
      "channel_name": "Marzell Crypto",
      "channel_id": "UCFkstwrug81AuLPZhV6O3BQ",
      "thumbnail": "https://i.ytimg.com/vi/jJ_5Lv0dESU/hqdefault.jpg",
      "published_at": 1764859896.0,
      "url": "https://www.youtube.com/watch?v=jJ_5Lv0dESU",
      "duration": "5:52",
      "view_count": 1281,
      "view_count_display": "1K",
      "like_count": 50,
      "like_count_display": "50",
      "comment_count": 109,
      "comment_count_display": "109",
      "channel_avatar": "https://yt3.ggpht.com/nQwqVfsPnoOVihS2uStAeIcFOXE_eLDX141ByjaywLCampvwbhgiZLqN98Kt-NySc7JQ4twc=s88-c-k-c0x00ffffff-no-rj"
    },
    {
      "video_id": "na9LpJZqDyY",
      "title": "\ud83d\udea8 BTC &amp; ETH: I AM WARNING YOU AGAIN!!!! LISTEN THIS TIME!!!!!",
      "description": "What a huge trap on bitcoin, ethereum and the rest of crypto!!! Beware and get ready now!!! AI Trading Club: ...",
      "channel_name": "Thomas Kralow",
      "channel_id": "UCBhORXMwPfJtNtsZcUJHO6w",
      "thumbnail": "https://i.ytimg.com/vi/na9LpJZqDyY/hqdefault.jpg",
      "published_at": 1764843699.0,
      "url": "https://www.youtube.com/watch?v=na9LpJZqDyY",
      "duration": "10:24",
      "view_count": 22348,
      "view_count_display": "22K",
      "like_count": 2901,
      "like_count_display": "3K",
      "comment_count": 45,
      "comment_count_display": "45",
      "channel_avatar": "https://yt3.ggpht.com/T6eylFzRoWiLFQnmessN-5t4QwDWnUobHhHyVJv92zGafMJHV8X4tbGxZU2iwgbzpc0Ec-BJPfY=s88-c-k-c0x00ffffff-no-rj"
    },
    {
      "video_id": "WKfvr4xlONs",
      "title": "These Levels Decide Everything for Ethereum Now",
      "description": "Ethereum (ETH) is approaching a critical point, and the next major move could define the trend for the months ahead. In this video ...",
      "channel_name": "HKCM GLOBAL",
      "channel_id": "UCvLnTGJQthqju38QPtaD64Q",
      "thumbnail": "https://i.ytimg.com/vi/WKfvr4xlONs/hqdefault.jpg",
      "published_at": 1764866845.0,
      "url": "https://www.youtube.com/watch?v=WKfvr4xlONs",
      "duration": "10:00",
      "view_count": 1399,
      "view_count_display": "1K",
      "like_count": 132,
      "like_count_display": "132",
      "comment_count": 5,
      "comment_count_display": "5",
      "channel_avatar": "https://yt3.ggpht.com/WRTWbGoklkuNoIUjDOuvvFoAZ2kVG8dguiFtCmW4nSqpakwJ8kKTFi7KcyIGcUPSIZ864HhfxQ=s88-c-k-c0x00ffffff-no-rj"
    },
    {
      "video_id": "rO3ZorrJ-ps",
      "title": "Ethereum Leads Rally\ud83d\udcc8Technical Analysis @TimWarrenTrades",
      "description": "Bitcoin steadied near weekly highs as concerns ease, but most altcoins remain weak. Market shows early signs of recovery ...",
      "channel_name": "Paul Barron Network",
      "channel_id": "UC4VPa7EOvObpyCRI4YKRQRw",
      "thumbnail": "https://i.ytimg.com/vi/rO3ZorrJ-ps/hqdefault.jpg",
      "published_at": 1764879234.0,
      "url": "https://www.youtube.com/watch?v=rO3ZorrJ-ps",
      "duration": "32:14",
      "view_count": 24510,
      "view_count_display": "25K",
      "like_count": 1224,
      "like_count_display": "1K",
      "comment_count": 85,
      "comment_count_display": "85",
      "channel_avatar": "https://yt3.ggpht.com/cjXiGAgHvgSASNMfzMHW7ZNU9dTAhof0VnmSh04y7dv2muMDR-JBuCKg3sI_QBLn_Bp2QGYY=s88-c-k-c0x00ffffff-no-rj"
    },
    {
      "video_id": "1Rj5LQ0dG_A",
      "title": "Ethereum Elliott Wave Update \u2013 Key Resistance Levels Ahead",
      "description": "This video provides a professional Elliott Wave and technical analysis of Ethereum (ETH), focusing on market structure, major ...",
      "channel_name": "More Crypto Online",
      "channel_id": "UCngIhBkikUe6e7tZTjpKK7Q",
      "thumbnail": "https://i.ytimg.com/vi/1Rj5LQ0dG_A/hqdefault.jpg",
      "published_at": 1764859756.0,
      "url": "https://www.youtube.com/watch?v=1Rj5LQ0dG_A",
      "duration": "4:44",
      "view_count": 2798,
      "view_count_display": "3K",
      "like_count": 203,
      "like_count_display": "203",
      "comment_count": 9,
      "comment_count_display": "9",
      "channel_avatar": "https://yt3.ggpht.com/lKp1RAXR6bdVGybEYj2J4_y6FLPK5ysaLw7-BHliSb2HGYYaQXj5IXPlFPtESnWy6HqQpycD=s88-c-k-c0x00ffffff-no-rj"
    },
    {
      "video_id": "iifblt4mU7o",
      "title": "Fusaka Is Live: Why The Ethereum Burn Rate Just Doubled.",
      "description": "The Ethereum network has fundamentally changed as of December 3rd. In this deep dive, we break down the immediate impact of ...",
      "channel_name": "Wall Street Stockcast",
      "channel_id": "UCdRRbGBhawlJ9GHpBeLa0iw",
      "thumbnail": "https://i.ytimg.com/vi/iifblt4mU7o/hqdefault.jpg",
      "published_at": 1764862224.0,
      "url": "https://www.youtube.com/watch?v=iifblt4mU7o",
      "duration": "10:55",
      "view_count": 3893,
      "view_count_display": "4K",
      "like_count": 119,
      "like_count_display": "119",
      "comment_count": 17,
      "comment_count_display": "17",
      "channel_avatar": "https://yt3.ggpht.com/k_g-riE9vXZ9_4phtxZ_BMmA7DCxVd87_JSX62Swt0HVpAxrVUyTXTICcqu2NRdHRqxrLno1=s88-c-k-c0x00ffffff-no-rj"
    },
    {
      "video_id": "ZeU2mtYr0Ok",
      "title": "Ethereum Elliott Wave Update \u2013 Key Resistance Levels Ahead",
      "description": "This video provides a professional Elliott Wave and technical analysis of Ethereum (ETH), focusing on market structure, major ...",
      "channel_name": "More Crypto Online",
      "channel_id": "UCngIhBkikUe6e7tZTjpKK7Q",
      "thumbnail": "https://i.ytimg.com/vi/ZeU2mtYr0Ok/hqdefault.jpg",
      "published_at": 1764895146.0,
      "url": "https://www.youtube.com/watch?v=ZeU2mtYr0Ok",
      "duration": "5:41",
      "view_count": 1613,
      "view_count_display": "2K",
      "like_count": 157,
      "like_count_display": "157",
      "comment_count": 10,
      "comment_count_display": "10",
      "channel_avatar": "https://yt3.ggpht.com/lKp1RAXR6bdVGybEYj2J4_y6FLPK5ysaLw7-BHliSb2HGYYaQXj5IXPlFPtESnWy6HqQpycD=s88-c-k-c0x00ffffff-no-rj"
    }
  ],
  "fetched_at": "2025-12-05T07:30:47.073759+00:00"
}