{
  "cached_at": "2025-11-27T17:40:39.336275+00:00",
  "data": {
    "url": "https://finance.yahoo.com/news/tom-lee-buys-ethereum-dip-163359923.html",
    "title": "Tom Lee buys Ethereum dip pushing BitMine\u2019s holdings to 3% of entire token supply",
    "description": "BitMine buys another $200 million worth of Ethereum. The firm now hold 3% of the token's entire supply.",
    "image": "https://s.yimg.com/ny/api/res/1.2/LSbjYMdNgT33doKBSa1hVw--/YXBwaWQ9aGlnaGxhbmRlcjt3PTEyMDA7aD03ODU-/https://media.zenfs.com/en/dlnews_702/148f88c251d17b1f4ad32e0543b5f72f",
    "favicon": "https://s.yimg.com/cv/apiv2/default/finance/favicon-180x180.png",
    "site_name": "Yahoo Finance",
    "author": null,
    "keywords": "Tom Lee, Bitcoin miner"
  }
}