{
  "cached_at": "2025-12-03T16:17:50.942553+00:00",
  "data": {
    "url": "https://www.prnewswire.com/news-releases/daimler-truck-and-torc-robotics-select-innoviz-technologies-as-lidar-partner-for-series-production-of-level-4-autonomous-trucks-302630271.html",
    "title": "Daimler Truck and Torc Robotics Select Innoviz Technologies as LiDAR Partner for Series Production of Level 4 Autonomous Trucks",
    "description": "/PRNewswire/ -- Innoviz Technologies Ltd. (NASDAQ: INVZ) (the \"Company\" or \"Innoviz\"), a leading Tier-1 direct supplier of high-performance, automotive-grade...",
    "image": "https://mma.prnewswire.com/media/2836337/Innoviz.jpg?p=facebook",
    "favicon": "https://www.prnewswire.com/content/dam/prnewswire/icons/2019-Q4-PRN-Icon-32-32.png",
    "site_name": null,
    "author": "Innoviz Technologies",
    "keywords": "Innoviz Technologies"
  }
}