{
  "url": "https://finance.yahoo.com/news/satoshi-nakamotos-bitcoin-wealth-falls-203341117.html",
  "cached_at": "2025-11-23T21:24:21.973856+00:00",
  "metadata": {
    "url": "https://finance.yahoo.com/news/satoshi-nakamotos-bitcoin-wealth-falls-203341117.html",
    "title": "Satoshi Nakamoto's Bitcoin Wealth Falls By $41 Billion, Now Poorer Than Bill Gates",
    "description": "Satoshi Nakamoto's Bitcoin-based net worth took a heavy hit as BTC dropped more than 30% from its all-time high set in October.",
    "image": "https://s.yimg.com/ny/api/res/1.2/jyzFqsbLCA9dkllXiCqJZA--/YXBwaWQ9aGlnaGxhbmRlcjt3PTEyMDA7aD02NzU-/https://media.zenfs.com/en/decrypt_157/154909b8c1ee44e54e9722cde1c4cc06",
    "favicon": "https://s.yimg.com/cv/apiv2/default/finance/favicon-180x180.png",
    "site_name": "Yahoo Finance",
    "author": null,
    "keywords": "Satoshi Nakamoto, Bitcoin, Forbes billionaires list, Bill Gates, Arkham Intelligence, net worth"
  }
}