{
  "cached_at": "2025-11-29T22:43:18.505082+00:00",
  "data": {
    "url": "https://finance.yahoo.com/news/kalshi-traders-price-bearish-odds-192255695.html",
    "title": "Kalshi Traders Price Bearish Odds on $100K Bitcoin Rebound in 2025",
    "description": "Bitcoin price rebounded 17%, moving from lows near $82,000 on November 21 to graze the $93,000 level on November 28. Bitcoin ETFs recorded a combined $221 million in net inflows between Nov. 25 and Nov. 28. Still, despite closing Friday with a modest $74 million net-positive session, BTC failed to ...",
    "image": "https://media.zenfs.com/en/coinspeaker_us_106/f79dba8c8d9b29e3266955f26454f4d9",
    "favicon": "https://s.yimg.com/cv/apiv2/default/finance/favicon-180x180.png",
    "site_name": "Yahoo Finance",
    "author": null,
    "keywords": "Bitcoin price, Kalshi, Keltner Channel"
  }
}