{
  "url": "https://finance.yahoo.com/news/satoshi-nakamotos-wealth-takes-34-201627290.html",
  "cached_at": "2025-11-22T20:38:03.572669",
  "metadata": {
    "url": "https://finance.yahoo.com/news/satoshi-nakamotos-wealth-takes-34-201627290.html",
    "title": "Satoshi Nakamoto's Wealth Takes a 34% Hit as Bitcoin Plummets",
    "description": "Satoshi Nakamoto, the elusive creator of Bitcoin (CRYPTO: BTC), has witnessed a 34% drop in his net worth, which now stands at $90.7 billion. What Happened: Nakamoto\u2019s estimated fortune has plummeted from its October peak of $137 billion. This substantial decline is a result of the ongoing downturn in the cryptocurrency market. The decrease, amounting to $47 billion, has pushed Nakamoto down to the 20th position on the Forbes billionaire list. He now ranks just behind Bill Gates, who has a net w",
    "image": "https://media.zenfs.com/en/Benzinga/5505c835398d78ba8a65e429cab15bcc",
    "favicon": "https://s.yimg.com/cv/apiv2/default/finance/favicon-180x180.png",
    "site_name": "Yahoo Finance",
    "author": null,
    "keywords": "Satoshi Nakamoto, Bill Gates, cryptocurrency market, substantial decline, market downturn, net worth, market instability"
  }
}