{
  "cached_at": "2025-11-24T18:39:41.659590+00:00",
  "data": {
    "url": "https://www.cnbc.com/2025/11/21/figure-ai-sued.html",
    "title": "Figure AI sued by whistleblower who warned that startup's robots could 'fracture a human skull'",
    "description": "A former engineer for Figure AI filed a lawsuit against the company, claiming he was unlawfully terminated after warning executives about product safety.",
    "image": "https://image.cnbcfm.com/api/v1/image/107379938-1709152661747-Figure_Image_4.jpg?v=1709153015&w=1920&h=1080",
    "favicon": "https://sc.cnbcfm.com/applications/cnbc.com/staticcontent/img/favicon.ico",
    "site_name": "CNBC",
    "author": "Lora Kolodny",
    "keywords": "Breaking News: Technology,Laws,Jeff Bezos,Jeff Bezos,Venture capital,Autos,Technology,NVIDIA Corp,Tesla Inc,business news"
  }
}