{
  "cached_at": "2025-12-03T19:57:19.584425+00:00",
  "data": {
    "url": "https://sg.finance.yahoo.com/news/ethereums-fusaka-upgrade-cements-networks-172345364.html",
    "title": "Ethereum's 'Fusaka' Upgrade Cements Network's Role as On-Chain Finance Settlement Layer: Bitwise",
    "description": "The upgrade will boost throughput, keep validators efficient and, most importantly, strengthen Ethereum's value capture by putting a floor under blob fees.",
    "image": "https://s.yimg.com/ny/api/res/1.2/WhANBarw938CCzsrLbuObw--/YXBwaWQ9aGlnaGxhbmRlcjt3PTEyMDA7aD02NzU-/https://media.zenfs.com/en/coindesk_75/db567a1bf42fd691fbc83fea9b3626e5",
    "favicon": "https://s.yimg.com/cv/apiv2/default/finance/favicon-180x180.png",
    "site_name": "Yahoo Finance",
    "author": null,
    "keywords": "Ethereum, Bitwise, Fusaka"
  }
}