{
  "cached_at": "2025-11-26T05:48:17.964688+00:00",
  "data": {
    "url": "https://digiday.com/marketing/how-consumers-are-using-ai-to-shop-in-2025-by-the-numbers/",
    "title": "How consumers are using AI to shop in 2025 \u2014\u00a0by the numbers",
    "description": "AI is reshaping the 2025 holiday shopping journey. Here's how brands are shifting SEO, budgets, and product data to be 'agent-ready.'",
    "image": "https://digiday.com/wp-content/uploads/sites/3/2025/11/brands-ai-positioning-digiday.jpg",
    "favicon": "https://digiday.com/wp-content/themes/digiday/static/images/favicons/apple-touch-icon.png",
    "site_name": "Digiday",
    "author": "Kimeko McCoy",
    "keywords": null
  }
}