{
  "cached_at": "2025-11-26T03:57:23.465865+00:00",
  "data": {
    "url": "https://247wallst.com/investing/2025/11/24/solanas-2-85b-revenue-explosion-why-it-could-outperform-ethereum-in-2026/",
    "title": "Solana's $2.85B Revenue Explosion: Why It Could Outperform Ethereum in 2026",
    "description": "Solana generated $2.85B in revenue vs Ethereum's declining fees. Will faster speeds and ETF momentum push SOL ahead of ETH in 2026?",
    "image": "https://247wallst.com/wp-content/uploads/2024/03/shutterstock-2051580854-huge-licensed-scaled.jpg",
    "favicon": "https://247wallst.com/favicon.ico",
    "site_name": "24/7 Wall St.",
    "author": "Sam Daodu",
    "keywords": null
  }
}