{
  "cached_at": "2025-12-01T21:20:46.125722+00:00",
  "data": {
    "url": "https://sherwood.news/crypto/ethereum-spot-etfs-post-highest-monthly-outflow-of-usd1-4-billion-in/",
    "title": "Ethereum spot ETFs post highest monthly outflow of $1.4 billion in November, breaking seven-month streak",
    "description": "Meanwhile, ethereum developers are preparing for the activation of Fusaka, the next network upgrade....",
    "image": "https://sherwoodnews.imgix.net/mwphzyq69oso/en-US/assets/files/538709913_man-reeling-from-explosion.jpg?w=1600&auto=compress%2Cformat&cs=srgb",
    "favicon": "https://cdn.robinhood.com/assets/sherwood/favicon/apple-touch-icon.png",
    "site_name": "Sherwood News",
    "author": null,
    "keywords": null
  }
}