{
  "cached_at": "2025-11-27T13:09:16.864909+00:00",
  "data": {
    "url": "https://spectrum.ieee.org/levi-unema-underwater-robotics-exploration",
    "title": "For This Engineer, Taking Deep Dives Is Part of the Job",
    "description": "What does it take to engineer robots that withstand ocean pressure? Levi Unema takes on the challenges of underwater exploration.",
    "image": "https://spectrum.ieee.org/media-library/image.png?id=62218869&width=1200&height=600&coordinates=0%2C521%2C0%2C522",
    "favicon": "https://assets.rebelmouse.io/eyJhbGciOiJIUzI1NiIsInR5cCI6IkpXVCJ9.eyJpbWFnZSI6Imh0dHBzOi8vYXNzZXRzLnJibC5tcy8yNjU5NjY0OS9vcmlnaW4ucG5nIiwiZXhwaXJlc19hdCI6MTc4NTc0NjUwNn0.pFbPADvK9fyfasig9FMci3xf6UeB_WJaER5Yea_eRpI/img.png?width=192&height=192",
    "site_name": "IEEE Spectrum",
    "author": null,
    "keywords": "type:departments, underwater robots, oceanography, noaa, rovs"
  }
}