{
  "cached_at": "2025-12-01T12:47:21.783169+00:00",
  "data": {
    "url": "https://www.genengnews.com/topics/artificial-intelligence/ai-designed-antibodies-achieve-atomic-precision-to-enhance-drug-discovery/",
    "title": "AI-Designed Antibodies Achieve Atomic Precision to Enhance Drug Discovery",
    "description": "David Baker\u2019s Nobel Prize winning lab has generated antibodies from scratch that target user-specified binding sites for AI therapeutic design.",
    "image": "https://www.genengnews.com/wp-content/uploads/2025/11/De_novo_antibody_Ian_Haydon.png",
    "favicon": "https://www.genengnews.com/wp-content/uploads/2018/10/gen-76x76.png",
    "site_name": "GEN - Genetic Engineering and Biotechnology News",
    "author": "Fay Lin, PhD",
    "keywords": null
  }
}