{
  "url": "https://finance.yahoo.com/news/oktas-okta-industry-recognition-ai-181101391.html",
  "cached_at": "2025-11-22T18:46:20.733037",
  "metadata": {
    "url": "https://finance.yahoo.com/news/oktas-okta-industry-recognition-ai-181101391.html",
    "title": "Can Okta's (OKTA) Industry Recognition and AI Push Strengthen Its Competitive Moat?",
    "description": "Okta was recognized as a Leader in the 2025 Gartner Magic Quadrant for Access Management for the ninth consecutive year and introduced new Auth0 Platform capabilities to support secure AI agent development and identity security fabric advancements. This recognition reinforces Okta's reputation for innovation at a time when organizations are seeking unified identity solutions for increasingly complex, AI-driven security needs. We'll take a look at how Okta's AI-focused product enhancements...",
    "image": "https://media.zenfs.com/en/simply_wall_st__316/47b1af040582d42464f0a0f280b2e22b",
    "favicon": "https://s.yimg.com/cv/apiv2/default/finance/favicon-180x180.png",
    "site_name": "Yahoo Finance",
    "author": null,
    "keywords": "Okta, identity solutions, industry recognition"
  }
}