{
  "cached_at": "2025-12-02T06:53:49.356136+00:00",
  "data": {
    "url": "https://www.ft.com/content/9d90d557-48e5-4f4b-a927-88071cef8ea9",
    "title": "UK pension funds dump US equities on fears of AI bubble",
    "description": "Public and private-sector funds concerned over market\u2019s growing concentration in a small number of tech stocks",
    "image": "https://images.ft.com/v3/image/raw/https%3A%2F%2Fd1e00ek4ebabms.cloudfront.net%2Fproduction%2F945ae5b2-ba68-4f8c-9f4d-31171ae8e801.jpg?source=next-barrier-page",
    "favicon": "https://images.ft.com/v3/image/raw/ftlogo-v1%3Abrand-ft-logo-square-coloured?source=page-kit&format=png&width=180&height=180",
    "site_name": null,
    "author": null,
    "keywords": null
  }
}