{
  "cached_at": "2025-11-24T18:39:19.001564+00:00",
  "data": {
    "url": "https://blog.bitjson.com/quantumroot-on-chipnet/",
    "title": "Post-quantum vaults are live on Bitcoin Cash's Chipnet",
    "description": "Quantumroot vaults are now live on Bitcoin Cash's 6-months-ahead preview network. Contracts, testing suite, and transaction generation code now available.",
    "image": "https://blog.bitjson.com/content/images/size/w1200/2025/11/quantumroot-sweep-1.png",
    "favicon": "https://blog.bitjson.com/content/images/size/w256h256/2021/04/bitjson-bitauth-favicon-1.png",
    "site_name": "bitjson's blog",
    "author": null,
    "keywords": null
  }
}