{
  "cached_at": "2025-11-30T17:25:38.950382+00:00",
  "data": {
    "url": "https://www.fool.com/investing/2025/11/30/1-new-reason-to-be-cautious-about-buying-ethereum/",
    "title": "1 New Reason to Be Cautious About Buying Ethereum, Solana, and XRP Right Now | The Motley Fool",
    "description": "If this widely touted growth driver peters out, it could spell big trouble.",
    "image": "https://g.foolcdn.com/image/?url=https%3A%2F%2Fg.foolcdn.com%2Feditorial%2Fimages%2F843801%2Fstanding-pair-of-investors-consider-tablet-and-computer.jpg&w=1200&op=resize",
    "favicon": "https://www.fool.com/favicon.ico",
    "site_name": "The Motley Fool",
    "author": "Alex Carchidi",
    "keywords": null
  }
}