{
  "cached_at": "2025-11-24T17:46:13.188057+00:00",
  "data": {
    "url": "https://github.com/Zleap-AI/SAG",
    "title": "GitHub - Zleap-AI/SAG: SAG - SQL\u9a71\u52a8\u7684RAG\u5f15\u64ce \u00b7 \u67e5\u8be2\u65f6\u81ea\u52a8\u6784\u5efa\u77e5\u8bc6\u56fe\u8c31 | SQL-Driven RAG Engine \u00b7 Automatically Build Knowledge Graph During Querying",
    "description": "SAG - SQL\u9a71\u52a8\u7684RAG\u5f15\u64ce \u00b7 \u67e5\u8be2\u65f6\u81ea\u52a8\u6784\u5efa\u77e5\u8bc6\u56fe\u8c31 | SQL-Driven RAG Engine \u00b7 Automatically Build Knowledge Graph During Querying - Zleap-AI/SAG",
    "image": "https://opengraph.githubassets.com/d69c3a3459df3344a794364f9b77e0fba1d1aebe7813f23952fcac697bf515c6/Zleap-AI/SAG",
    "favicon": "https://github.githubassets.com/favicons/favicon.png",
    "site_name": "GitHub",
    "author": null,
    "keywords": null
  }
}