{
  "cached_at": "2025-11-24T20:39:06.568936+00:00",
  "data": {
    "url": "https://fortune.com/crypto/2025/11/24/bitcoin-price-today-fundamentals-crypto-markets-down/",
    "title": "Here\u2019s how low Bitcoin is likely to fall | Fortune Crypto",
    "description": "Bitcoin nearly fell below $80,000 and it could get worse. But the fundamentals are different this time.",
    "image": "https://fortune.com/img-assets/wp-content/uploads/2025/11/Crypto-Volatility-4.jpg?resize=1200,600",
    "favicon": "https://fortune.com/icons/favicons/apple-touch-icon.png",
    "site_name": "Fortune Crypto",
    "author": "Jeff John Roberts",
    "keywords": null
  }
}