{
  "coin_id": "bitcoin",
  "name": "Bitcoin",
  "symbol": "BTC",
  "current_price": 90627,
  "market_cap": 1808477083826,
  "total_supply": 19955240.0,
  "circulating_supply": 19955240.0,
  "max_supply": 21000000.0,
  "ath": {
    "price": 126080,
    "date": "2025-10-06T18:57:42.558Z",
    "change_percent": -28.11944796954315
  },
  "atl": {
    "price": 67.81,
    "date": "2013-07-06T00:00:00.000Z",
    "change_percent": 133548.42943518655
  },
  "price_change_24h_percent": -1.08562,
  "market_cap_rank": 1,
  "fetched_at": "2025-11-29T10:47:23.033181+00:00"
}