{
  "title": "YouTube Videos",
  "query": "bitcoin",
  "order": "relevance",
  "videos": [
    {
      "video_id": "G4arrKN_1gQ",
      "title": "\u201cWhy This Bitcoin Crash Is Actually Bullish\u201d | Anthony Scaramucci",
      "description": "Bitcoin #Crypto #Finance Bitcoin has surged 5x since 2023... but according to Anthony Scaramucci, the real bull market hasn't ...",
      "channel_name": "The Wolf Of All Streets",
      "channel_id": "UCxIU1RFIdDpvA8VOITswQ1A",
      "thumbnail": "https://i.ytimg.com/vi/G4arrKN_1gQ/hqdefault.jpg",
      "published_at": 1763906432.0,
      "url": "https://www.youtube.com/watch?v=G4arrKN_1gQ",
      "duration": "53:11",
      "view_count": 37300,
      "view_count_display": "37K",
      "like_count": 1771,
      "like_count_display": "2K",
      "comment_count": 470,
      "comment_count_display": "470",
      "channel_avatar": "https://yt3.ggpht.com/sbIsQzXcVdEYKEqm7FweTsTyh79je4SyULX9gVVsMaat6YgOsEmFywmcfzXGFgXf1RcnXtfk=s88-c-k-c0x00ffffff-no-rj"
    },
    {
      "video_id": "xBhd-rAIOsE",
      "title": "THE THEORY OF WHY BITCOIN DUMPED IS GETTING WEIRD...",
      "description": "Up to *$30000* Welcome Bonus]\u25c5 \u2713 *NO RESTRICTIONS* IF YOU *Use THIS Link* Phemex Exchange ...",
      "channel_name": "Tyler S",
      "channel_id": "UCgBQ6YsN4oUTjbAvIwCFLog",
      "thumbnail": "https://i.ytimg.com/vi/xBhd-rAIOsE/hqdefault.jpg",
      "published_at": 1763921524.0,
      "url": "https://www.youtube.com/watch?v=xBhd-rAIOsE",
      "duration": "11:48",
      "view_count": 21161,
      "view_count_display": "21K",
      "like_count": 1051,
      "like_count_display": "1K",
      "comment_count": 311,
      "comment_count_display": "311",
      "channel_avatar": "https://yt3.ggpht.com/zGapl5vYcAyoAWfUDZWhwS7QtE-icYXQ7NtJeRIn9I6xY6wYRLaudyu6yPf7MLKpd-DiGxwfolE=s88-c-k-c0x00ffffff-no-rj"
    },
    {
      "video_id": "BYCjRF6FRe8",
      "title": "BOMBSHELL: I Just Discovered What\u2019s REALLY Going On With Crypto",
      "description": "BOMBSHELL: I Just Discovered What's REALLY Going On With Crypto 50% deposit bonus on first $100 - (sign up on WEEX): ...",
      "channel_name": "Altcoin Daily",
      "channel_id": "UCbLhGKVY-bJPcawebgtNfbw",
      "thumbnail": "https://i.ytimg.com/vi/BYCjRF6FRe8/hqdefault.jpg",
      "published_at": 1763936449.0,
      "url": "https://www.youtube.com/watch?v=BYCjRF6FRe8",
      "duration": "13:54",
      "view_count": 30747,
      "view_count_display": "31K",
      "like_count": 2257,
      "like_count_display": "2K",
      "comment_count": 195,
      "comment_count_display": "195",
      "channel_avatar": "https://yt3.ggpht.com/ytc/AIdro_ndZORygyaaS9NAs9gaLWYqTdF3NSmsKoZoSzWtRRtslUI=s88-c-k-c0x00ffffff-no-rj"
    },
    {
      "video_id": "myYZwGIRrdU",
      "title": "BITCOIN THIS IS IT!!",
      "description": "CHECK OUT MY LINKTREE FOR EXCHANGES I USE, BONUSES, FREE VIDEOS, AND MORE! https://linktr.ee/Myfinancialfriend I ...",
      "channel_name": "My Financial Friend",
      "channel_id": "UCUr_YzOB7pp50F4r1KJ7Dag",
      "thumbnail": "https://i.ytimg.com/vi/myYZwGIRrdU/hqdefault.jpg",
      "published_at": 1763912708.0,
      "url": "https://www.youtube.com/watch?v=myYZwGIRrdU",
      "duration": "15:09",
      "view_count": 19409,
      "view_count_display": "19K",
      "like_count": 883,
      "like_count_display": "883",
      "comment_count": 229,
      "comment_count_display": "229",
      "channel_avatar": "https://yt3.ggpht.com/ytc/AIdro_mgdUCgLuKZTCP6-UIc9MgDQkamZcBl6BQdq3-lOUwPi-M=s88-c-k-c0x00ffffff-no-rj"
    },
    {
      "video_id": "XZagbBdzs24",
      "title": "Ripple XRP IT&#39;S RIGGED: \u201cBITCOIN IS GOING TO ZERO!\u201d Dan Pena | THIS HAPPENS NEXT! (WILD CRYPTO NEWS)",
      "description": "Enter code 777 on checkout to get the maximum discount on your $100k - 200k funded account: ...",
      "channel_name": "BULLRUNNERS",
      "channel_id": "UCpafWgLqheRAbCjOJAxDwAw",
      "thumbnail": "https://i.ytimg.com/vi/XZagbBdzs24/hqdefault.jpg",
      "published_at": 1763940895.0,
      "url": "https://www.youtube.com/watch?v=XZagbBdzs24",
      "duration": "27:57",
      "view_count": 9502,
      "view_count_display": "10K",
      "like_count": 458,
      "like_count_display": "458",
      "comment_count": 146,
      "comment_count_display": "146",
      "channel_avatar": "https://yt3.ggpht.com/Nc__UjQwYPm1Wu2xtgZWVMvWGeM-Q0r3o8v0fiMS432_eDAmOgqCedggTk8YyoXBDuWcIKoD=s88-c-k-c0x00ffffff-no-rj"
    },
    {
      "video_id": "pbtfyTdw3f4",
      "title": "Crypto Hodlers: I Don&#39;t Want To FRIGHTEN You But Please PREPARE YOURSELF",
      "description": "LIMITED TIME: 50% deposit bonus on first $100 - sign up on WEEX): https://www.weex.com/events/welcome-event?",
      "channel_name": "Altcoin Daily",
      "channel_id": "UCbLhGKVY-bJPcawebgtNfbw",
      "thumbnail": "https://i.ytimg.com/vi/pbtfyTdw3f4/hqdefault.jpg",
      "published_at": 1763856701.0,
      "url": "https://www.youtube.com/watch?v=pbtfyTdw3f4",
      "duration": "12:22",
      "view_count": 84247,
      "view_count_display": "84K",
      "like_count": 4730,
      "like_count_display": "5K",
      "comment_count": 485,
      "comment_count_display": "485",
      "channel_avatar": "https://yt3.ggpht.com/ytc/AIdro_ndZORygyaaS9NAs9gaLWYqTdF3NSmsKoZoSzWtRRtslUI=s88-c-k-c0x00ffffff-no-rj"
    },
    {
      "video_id": "xwJUJbNUDp8",
      "title": "The Bitcoin Crash is about to Get MUCH Worse.",
      "description": "Helium Mobile: Sign up (even for the FREE plan) & get $10 in Cloud Points with code KEVIN: ...",
      "channel_name": "Meet Kevin",
      "channel_id": "UCUvvj5lwue7PspotMDjk5UA",
      "thumbnail": "https://i.ytimg.com/vi/xwJUJbNUDp8/hqdefault.jpg",
      "published_at": 1763850784.0,
      "url": "https://www.youtube.com/watch?v=xwJUJbNUDp8",
      "duration": "14:18",
      "view_count": 109940,
      "view_count_display": "110K",
      "like_count": 3128,
      "like_count_display": "3K",
      "comment_count": 655,
      "comment_count_display": "655",
      "channel_avatar": "https://yt3.ggpht.com/UNKoK2tlOGQXafXouqfODf77MFKeUa6I0H-K3r19ziuFwEez7FIhOaG05FEL-yezRjHpfUwzVg=s88-c-k-c0x00ffffff-no-rj"
    },
    {
      "video_id": "CSoitulM6Ac",
      "title": "Bitcoin Elliott Wave Update \u2013 A Major Decision Point Ahead for BTC",
      "description": "This video provides a professional Elliott Wave and technical analysis of Bitcoin (BTC), focusing on market structure, key support ...",
      "channel_name": "More Crypto Online",
      "channel_id": "UCngIhBkikUe6e7tZTjpKK7Q",
      "thumbnail": "https://i.ytimg.com/vi/CSoitulM6Ac/hqdefault.jpg",
      "published_at": 1763923960.0,
      "url": "https://www.youtube.com/watch?v=CSoitulM6Ac",
      "duration": "3:56",
      "view_count": 7057,
      "view_count_display": "7K",
      "like_count": 471,
      "like_count_display": "471",
      "comment_count": 10,
      "comment_count_display": "10",
      "channel_avatar": "https://yt3.ggpht.com/lKp1RAXR6bdVGybEYj2J4_y6FLPK5ysaLw7-BHliSb2HGYYaQXj5IXPlFPtESnWy6HqQpycD=s88-c-k-c0x00ffffff-no-rj"
    },
    {
      "video_id": "h0hssJ3kDx8",
      "title": "Morgan Stanley CRASHES Crypto! ($74K Bitcoin NEXT?)",
      "description": "Deezy look sat the latest rebalancing recommendations from Morgan Stanley for their MSCI (Morgan Stanley Capital ...",
      "channel_name": "Discover Crypto",
      "channel_id": "UCjemQfjaXAzA-95RKoy9n_g",
      "thumbnail": "https://i.ytimg.com/vi/h0hssJ3kDx8/hqdefault.jpg",
      "published_at": 1763856048.0,
      "url": "https://www.youtube.com/watch?v=h0hssJ3kDx8",
      "duration": "7:04",
      "view_count": 12226,
      "view_count_display": "12K",
      "like_count": 424,
      "like_count_display": "424",
      "comment_count": 83,
      "comment_count_display": "83",
      "channel_avatar": "https://yt3.ggpht.com/ByeOVnzg4NGjB901wnWg3mmKPG6_kUXGqOLhrGs7-adpkZ3YCUsNcvTwDEcV_XOT-i7HOIla=s88-c-k-c0x00ffffff-no-rj"
    },
    {
      "video_id": "YKCdDAbws4o",
      "title": "Bitcoin Fear Hits All-Time High - What Happens Now?",
      "description": "Jordi Visser (@JordiVisserLabs) is a macro investor with over 30 years of Wall Street experience. He also writes a Substack called ...",
      "channel_name": "Anthony Pompliano",
      "channel_id": "UCevXpeL8cNyAnww-NqJ4m2w",
      "thumbnail": "https://i.ytimg.com/vi/YKCdDAbws4o/hqdefault.jpg",
      "published_at": 1763820057.0,
      "url": "https://www.youtube.com/watch?v=YKCdDAbws4o",
      "duration": "46:17",
      "view_count": 123333,
      "view_count_display": "123K",
      "like_count": 4495,
      "like_count_display": "4K",
      "comment_count": 187,
      "comment_count_display": "187",
      "channel_avatar": "https://yt3.ggpht.com/ytc/AIdro_nXpePpIKrZ3H8WBZT6POzIWOY7UZc70rPS2dzTs2bvhnQ=s88-c-k-c0x00ffffff-no-rj"
    }
  ],
  "fetched_at": "2025-11-24T04:06:18.541826+00:00"
}