{
  "title": "YouTube Videos",
  "query": "bitcoin",
  "order": "relevance",
  "videos": [
    {
      "video_id": "fE1XaJjBwkg",
      "title": "bitcoin is about to change forever (and nobody even realises)",
      "description": "bitcoin is having some massive changes and I see nobody talking about them. future is bright fam Check out Casa's free guide on ...",
      "channel_name": "BTC Isla",
      "channel_id": "UCiTTivZ3-WYophxSkV_UiKQ",
      "thumbnail": "https://i.ytimg.com/vi/fE1XaJjBwkg/hqdefault.jpg",
      "published_at": 1764954028.0,
      "url": "https://www.youtube.com/watch?v=fE1XaJjBwkg",
      "duration": "10:23",
      "view_count": 22716,
      "view_count_display": "23K",
      "like_count": 1819,
      "like_count_display": "2K",
      "comment_count": 321,
      "comment_count_display": "321",
      "channel_avatar": "https://yt3.ggpht.com/877slsbdEuUIAiU_JvqDxSzMGTGut40fSPAHEtsDWDNcnZiR8YS9T1j62ic4L7xdSmhZ1JofXrc=s88-c-k-c0x00ffffff-no-rj"
    },
    {
      "video_id": "CIvIjByD7pM",
      "title": "Is Bitcoin Going to ZERO or $1,000,000?",
      "description": "Everyone is screaming that Bitcoin is either going to zero or hitting a million but history says something very different. In this video ...",
      "channel_name": "Simply Bitcoin",
      "channel_id": "UCB6Q0S1gUHXMe5-Jjx0_laQ",
      "thumbnail": "https://i.ytimg.com/vi/CIvIjByD7pM/hqdefault.jpg",
      "published_at": 1764972013.0,
      "url": "https://www.youtube.com/watch?v=CIvIjByD7pM",
      "duration": "12:20",
      "view_count": 21961,
      "view_count_display": "22K",
      "like_count": 1483,
      "like_count_display": "1K",
      "comment_count": 260,
      "comment_count_display": "260",
      "channel_avatar": "https://yt3.ggpht.com/WVcU0m29P-EaxcDCV1ekVnZRGLlin0H4N56C9MlDB7kZk5bIKk8fRKEsaBl-zV4HVNTPNNO9=s88-c-k-c0x00ffffff-no-rj"
    },
    {
      "video_id": "0T4wVBhaO6s",
      "title": "Tom Lee - &quot;Biggest Crypto Reset EVER&quot; | Bitcoin &amp; ETH Price Prediction",
      "description": "FREE Daily On-Chain Analysis & Crypto News In 5-Mins: http://bit.ly/TheCryptoNutshell Watch The FULL Interview: \"Tom ...",
      "channel_name": "Library Of Wealth",
      "channel_id": "UC6OOQMJYX09OyrSRPABNxhA",
      "thumbnail": "https://i.ytimg.com/vi/0T4wVBhaO6s/hqdefault.jpg",
      "published_at": 1764912105.0,
      "url": "https://www.youtube.com/watch?v=0T4wVBhaO6s",
      "duration": "15:38",
      "view_count": 17809,
      "view_count_display": "18K",
      "like_count": 419,
      "like_count_display": "419",
      "comment_count": 368,
      "comment_count_display": "368",
      "channel_avatar": "https://yt3.ggpht.com/vIGkGx_lrJVM1ltCpqa2NG48qWilNEOEhFnvDGmXkPePpwgRS8e48sZofvuoNagZFrHeiZZCjg=s88-c-k-c0x00ffffff-no-rj"
    },
    {
      "video_id": "sU3cb55xCGo",
      "title": "WAIT: JP Morgan is STILL predicting $170,000 Bitcoin in 2026?! | EP 1392",
      "description": "After FUDing bitcoin and Strategy JP Morgan analysts are still predicting the 4 year cycle is over?",
      "channel_name": "Simply Bitcoin",
      "channel_id": "UCB6Q0S1gUHXMe5-Jjx0_laQ",
      "thumbnail": "https://i.ytimg.com/vi/sU3cb55xCGo/hqdefault.jpg",
      "published_at": 1764962996.0,
      "url": "https://www.youtube.com/watch?v=sU3cb55xCGo",
      "duration": "1:34:16",
      "view_count": 8462,
      "view_count_display": "8K",
      "like_count": 407,
      "like_count_display": "407",
      "comment_count": 54,
      "comment_count_display": "54",
      "channel_avatar": "https://yt3.ggpht.com/WVcU0m29P-EaxcDCV1ekVnZRGLlin0H4N56C9MlDB7kZk5bIKk8fRKEsaBl-zV4HVNTPNNO9=s88-c-k-c0x00ffffff-no-rj"
    },
    {
      "video_id": "5txYvyuM4uE",
      "title": "Bitcoin: A Different Kind of Bear Market?",
      "description": "Is Bitcoin in a different type of bear market? Let's discuss what a bear market may look like coming from a non-euphoric top.",
      "channel_name": "Benjamin Cowen",
      "channel_id": "UCRvqjQPSeaWn-uEx-w0XOIg",
      "thumbnail": "https://i.ytimg.com/vi/5txYvyuM4uE/hqdefault.jpg",
      "published_at": 1764934094.0,
      "url": "https://www.youtube.com/watch?v=5txYvyuM4uE",
      "duration": "15:38",
      "view_count": 90256,
      "view_count_display": "90K",
      "like_count": 5911,
      "like_count_display": "6K",
      "comment_count": 408,
      "comment_count_display": "408",
      "channel_avatar": "https://yt3.ggpht.com/tg4I_l0RHjgub4pVwa8UIrk64TnJKUINXjS0AfjHLG79PkWh8zg83IFsJHu1HcWhf9kUJyOLRT0=s88-c-k-c0x00ffffff-no-rj"
    },
    {
      "video_id": "RmFwVDHzkis",
      "title": "Bitcoin investors...Get Ready For Inflation Numbers and the Fed!",
      "description": "Exchange Partners** Bitunix Exchange \u25bb *$100000 Deposit Bonus* \u25bb https://bit.ly/3Tmp1Hq BTCC Exchange \u25bb *10% ...",
      "channel_name": "CryptosRUs",
      "channel_id": "UCI7M65p3A-D3P4v5qW8POxQ",
      "thumbnail": "https://i.ytimg.com/vi/RmFwVDHzkis/hqdefault.jpg",
      "published_at": 1764945033.0,
      "url": "https://www.youtube.com/watch?v=RmFwVDHzkis",
      "duration": "10:13",
      "view_count": 31197,
      "view_count_display": "31K",
      "like_count": 1507,
      "like_count_display": "2K",
      "comment_count": 330,
      "comment_count_display": "330",
      "channel_avatar": "https://yt3.ggpht.com/ytc/AIdro_mpKY9I7FUShJOGvuOsCaspa8lvJaRlDrkgA9oyTqx14qo=s88-c-k-c0x00ffffff-no-rj"
    },
    {
      "video_id": "3rSaeVkFY4Q",
      "title": "Every Major Bank Just Pivoted to Bitcoin\u2026 They Know What\u2019s Coming!",
      "description": "Every major economy is hitting the debt wall simultaneously. A global reset is coming\u2014fast, systemic, and total. BlackRock ...",
      "channel_name": "Simply Bitcoin",
      "channel_id": "UCB6Q0S1gUHXMe5-Jjx0_laQ",
      "thumbnail": "https://i.ytimg.com/vi/3rSaeVkFY4Q/hqdefault.jpg",
      "published_at": 1764895999.0,
      "url": "https://www.youtube.com/watch?v=3rSaeVkFY4Q",
      "duration": "23:27",
      "view_count": 48745,
      "view_count_display": "49K",
      "like_count": 3718,
      "like_count_display": "4K",
      "comment_count": 274,
      "comment_count_display": "274",
      "channel_avatar": "https://yt3.ggpht.com/WVcU0m29P-EaxcDCV1ekVnZRGLlin0H4N56C9MlDB7kZk5bIKk8fRKEsaBl-zV4HVNTPNNO9=s88-c-k-c0x00ffffff-no-rj"
    },
    {
      "video_id": "1no2ashJSIU",
      "title": "Michael Saylor: &quot;I&#39;m More Bullish Than EVER on Bitcoin!&quot;",
      "description": "Michael Saylor isn't just bullish \u2014 he's placing Bitcoin inside a countdown. By 2035, he says 99% of all Bitcoin will have been ...",
      "channel_name": "The Bitcoin Revolution",
      "channel_id": "UCr8ZlC6iUhMUvGNziD4H7Yg",
      "thumbnail": "https://i.ytimg.com/vi/1no2ashJSIU/hqdefault.jpg",
      "published_at": 1764950406.0,
      "url": "https://www.youtube.com/watch?v=1no2ashJSIU",
      "duration": "13:29",
      "view_count": 1752,
      "view_count_display": "2K",
      "like_count": 68,
      "like_count_display": "68",
      "comment_count": 60,
      "comment_count_display": "60",
      "channel_avatar": "https://yt3.ggpht.com/Tgicu8eXLD27FbLROxa0P9NSUnXCxymomp8UxeW0Zhq1FeaVrI7MdBLuYtox1O3qIQEkXXZC=s88-c-k-c0x00ffffff-no-rj"
    },
    {
      "video_id": "nrSuqkGl1t4",
      "title": "What Happens to Bitcoin When the Fed Finally Cuts?",
      "description": "Darius Dale is the Founder & CEO of 42 Macro. In this conversation, we break down the growing divisions inside the Federal ...",
      "channel_name": "Anthony Pompliano",
      "channel_id": "UCevXpeL8cNyAnww-NqJ4m2w",
      "thumbnail": "https://i.ytimg.com/vi/nrSuqkGl1t4/hqdefault.jpg",
      "published_at": 1764885659.0,
      "url": "https://www.youtube.com/watch?v=nrSuqkGl1t4",
      "duration": "28:20",
      "view_count": 25728,
      "view_count_display": "26K",
      "like_count": 944,
      "like_count_display": "944",
      "comment_count": 27,
      "comment_count_display": "27",
      "channel_avatar": "https://yt3.ggpht.com/ytc/AIdro_nXpePpIKrZ3H8WBZT6POzIWOY7UZc70rPS2dzTs2bvhnQ=s88-c-k-c0x00ffffff-no-rj"
    },
    {
      "video_id": "EKFoAAvZjbE",
      "title": "Bitcoin Shorts ABOUT TO GET DESTROYED - BlackRock&#39;s Confession Changes Everything",
      "description": "BLACKROCKS SHOCKING CRYPTO CONFESSION WHILE $3 BILLION BITCOIN SHORTS READY TO EXPLODE! iTrustCapital ...",
      "channel_name": "CryptoWendyO",
      "channel_id": "UCla2jS8BrfLJj7kbKyy5_ew",
      "thumbnail": "https://i.ytimg.com/vi/EKFoAAvZjbE/hqdefault.jpg",
      "published_at": 1764874754.0,
      "url": "https://www.youtube.com/watch?v=EKFoAAvZjbE",
      "duration": "25:26",
      "view_count": 6399,
      "view_count_display": "6K",
      "like_count": 515,
      "like_count_display": "515",
      "comment_count": 34,
      "comment_count_display": "34",
      "channel_avatar": "https://yt3.ggpht.com/ytc/AIdro_ltFsbT0IUR-gf8in7QG71jlXV5Eb1772v1D0QQdH9k5Nc=s88-c-k-c0x00ffffff-no-rj"
    }
  ],
  "fetched_at": "2025-12-06T08:19:18.034378+00:00"
}